[{"id":"a98827a0-4868-4d3b-ad93-0a04b51ffaa7","discipline_id":"CEA038","period":1,"prerequisites":"","mandatory":true,"course_id":"engenharia-de-computacao"},{"id":"e0a13086-5a34-42a4-832b-0078fe2c68bb","discipline_id":"CEA039","period":1,"prerequisites":"","mandatory":true,"course_id":"engenharia-de-computacao"},{"id":"8bc41fbd-0d20-41ae-bddb-3b11f40cd8b0","discipline_id":"CEA049","period":1,"prerequisites":"","mandatory":true,"course_id":"engenharia-de-computacao"},{"id":"4343bbb6-8f3e-4e26-9b9f-2e98bc9b5345","discipline_id":"CEA050","period":1,"prerequisites":"","mandatory":true,"course_id":"engenharia-de-computacao"},{"id":"13653ae5-2708-4c7b-98af-d891548ef98e","discipline_id":"CSI030","period":1,"prerequisites":"","mandatory":true,"course_id":"engenharia-de-computacao"},{"id":"64faea74-eb81-4725-a9dc-f0d1e9faab05","discipline_id":"CSI201","period":1,"prerequisites":"","mandatory":true,"course_id":"engenharia-de-computacao"},{"id":"3ebf639e-0a9d-4848-9294-0f1b72eaa719","discipline_id":"CSI427","period":1,"prerequisites":"","mandatory":true,"course_id":"engenharia-de-computacao"},{"id":"2fa37b72-a2cf-4c9a-9c15-a46937c2d8e5","discipline_id":"EAD707","period":1,"prerequisites":"","mandatory":true,"course_id":"engenharia-de-computacao"},{"id":"eff6c858-bcc1-4080-bd05-d105c8a2c12a","discipline_id":"CEA051","period":2,"prerequisites":"CEA049 CEA050","mandatory":true,"course_id":"engenharia-de-computacao"},{"id":"aa921590-35c1-4480-8f98-634678476497","discipline_id":"CEA055","period":2,"prerequisites":"CEA050","mandatory":true,"course_id":"engenharia-de-computacao"},{"id":"1b9b78b4-c36c-4962-ad6e-dd1b3d17be82","discipline_id":"CEA061","period":2,"prerequisites":"CEA049 CEA050","mandatory":true,"course_id":"engenharia-de-computacao"},{"id":"e2cb4c87-d109-4246-bb97-5eb107eb64c7","discipline_id":"CSI032","period":2,"prerequisites":"CSI030","mandatory":true,"course_id":"engenharia-de-computacao"},{"id":"ed4b97b2-3231-483d-a4a3-6a6fa63b059a","discipline_id":"CSI443","period":2,"prerequisites":"","mandatory":true,"course_id":"engenharia-de-computacao"},{"id":"48066bf0-86c1-4b0a-a13e-d88dfc6d51b6","discipline_id":"CEA052","period":3,"prerequisites":"CEA051","mandatory":true,"course_id":"engenharia-de-computacao"},{"id":"9a45d9d3-aa66-41c6-a5d7-5d190d8345c5","discipline_id":"CEA056","period":3,"prerequisites":"CEA051","mandatory":true,"course_id":"engenharia-de-computacao"},{"id":"756eb53f-8670-49c2-81cb-8bdf8d96e7ee 4954cd02-98d0-4d96-aec1-37446d421b49","discipline_id":"CEA062","period":"3","prerequisites":"CEA038 CEA039 CEA051 CEA061","mandatory":true,"course_id":"engenharia-de-computacao"},{"id":"45bba363-1b2d-4150-a845-32e86bba306c","discipline_id":"CEA341","period":3,"prerequisites":"CSI030","mandatory":true,"course_id":"engenharia-de-computacao"},{"id":"04c433cc-f91b-41f0-8bf3-e1ac0ea581d7","discipline_id":"CSI488","period":3,"prerequisites":"CSI030","mandatory":true,"course_id":"engenharia-de-computacao"},{"id":"c286e59f-cf04-4448-990a-1f064c62dc50 d1058adf-7d50-4cfd-8de9-81de6fbe38b7","discipline_id":"CEA063","period":"4","prerequisites":"CEA038 CEA039 CEA051 CEA055 CEA061","mandatory":true,"course_id":"engenharia-de-computacao"},{"id":"c704cb22-83d6-462b-9c96-83b558240f0b","discipline_id":"CEA552","period":4,"prerequisites":"CEA056 CEA062","mandatory":true,"course_id":"engenharia-de-computacao"},{"id":"02fbb545-5b0b-4d3f-b622-03614b3fad51","discipline_id":"CEA562","period":4,"prerequisites":"CEA056","mandatory":true,"course_id":"engenharia-de-computacao"},{"id":"2195d08d-bcd4-4959-a149-c2c0dc8e92f3","discipline_id":"CSI429","period":4,"prerequisites":"CSI032 CSI488","mandatory":true,"course_id":"engenharia-de-computacao"},{"id":"5bddf17b-de9f-4fb2-81a9-7ca683ff3ea1","discipline_id":"CSI466","period":4,"prerequisites":"CSI443 CSI488","mandatory":true,"course_id":"engenharia-de-computacao"},{"id":"39b47622-8a1d-45ad-b466-4d3dea17f74d f8cbb846-5737-4d41-a992-64dfdc280128","discipline_id":"CEA064","period":"5","prerequisites":"CEA052 CEA056 CEA062 CEA063","mandatory":true,"course_id":"engenharia-de-computacao"},{"id":"52fea446-b8a4-4818-a047-3ebf749797a1","discipline_id":"CEA502","period":5,"prerequisites":"CEA052 CEA063 CEA552","mandatory":true,"course_id":"engenharia-de-computacao"},{"id":"e55899a6-d309-4140-97bb-297160ee520c","discipline_id":"CSI148","period":5,"prerequisites":"CEA056 CSI030","mandatory":true,"course_id":"engenharia-de-computacao"},{"id":"7ef62664-ee28-45a9-bd42-8cb0750a11f1","discipline_id":"CSI203","period":5,"prerequisites":"CEA341 CSI030","mandatory":true,"course_id":"engenharia-de-computacao"},{"id":"4fa780b0-4901-48a4-9e42-80b86c43568e","discipline_id":"CSI485","period":5,"prerequisites":"CSI032 CSI488","mandatory":true,"course_id":"engenharia-de-computacao"},{"id":"4ffc71ed-3b59-4037-9428-6f953b5f57b9","discipline_id":"CEA561","period":6,"prerequisites":"CEA552","mandatory":true,"course_id":"engenharia-de-computacao"},{"id":"9496e418-eea1-4b64-abb7-22665dfd9776","discipline_id":"CEA582","period":6,"prerequisites":"CEA562","mandatory":true,"course_id":"engenharia-de-computacao"},{"id":"daf06055-38bf-4785-a0da-4ff232272a0f","discipline_id":"CSI440","period":6,"prerequisites":"CSI488","mandatory":true,"course_id":"engenharia-de-computacao"},{"id":"bcdf1601-091f-4d80-9e81-062689106596","discipline_id":"CSI509","period":6,"prerequisites":"CSI203","mandatory":true,"course_id":"engenharia-de-computacao"},{"id":"c63faa15-f80b-4b04-8aab-0075fabe4530","discipline_id":"CSI546","period":6,"prerequisites":"CSI466","mandatory":true,"course_id":"engenharia-de-computacao"},{"id":"2a3b18d7-a565-461c-ad0e-3a281c7cd1ab","discipline_id":"CEA551","period":7,"prerequisites":"CEA064 CEA552 CSI148","mandatory":true,"course_id":"engenharia-de-computacao"},{"id":"c179688a-00d2-4a8e-9c0a-97536f5aed28","discipline_id":"CEA580","period":7,"prerequisites":"CSI203","mandatory":true,"course_id":"engenharia-de-computacao"},{"id":"fd0a56a9-3b07-4c3e-99de-d3e96db69a54","discipline_id":"CSI437","period":7,"prerequisites":"CSI203 CSI488","mandatory":true,"course_id":"engenharia-de-computacao"},{"id":"0554ddfc-70e2-4031-b0df-e8e6a1db9697","discipline_id":"CSI476","period":7,"prerequisites":"CSI466","mandatory":true,"course_id":"engenharia-de-computacao"},{"id":"c08ac4a7-0a16-4690-8d5a-ae46e69eb387","discipline_id":"CSI508","period":7,"prerequisites":"CSI488","mandatory":true,"course_id":"engenharia-de-computacao"},{"id":"0051a2cf-06b0-41cd-9ade-041e82bdb985","discipline_id":"CSI419","period":8,"prerequisites":"CSI476","mandatory":true,"course_id":"engenharia-de-computacao"},{"id":"e7cb5ffe-c7f6-4f66-8eb7-a1b82b3dd30f","discipline_id":"CSI450","period":8,"prerequisites":"CSI485","mandatory":true,"course_id":"engenharia-de-computacao"},{"id":"04764043-e1f9-4487-b7f2-66c1db16a872","discipline_id":"CSI457","period":8,"prerequisites":"CSI466","mandatory":true,"course_id":"engenharia-de-computacao"},{"id":"784518ec-96e1-4ecd-b8eb-9810aad01ced","discipline_id":"CSI548","period":8,"prerequisites":"CSI488","mandatory":true,"course_id":"engenharia-de-computacao"},{"id":"c5b61314-e35d-4981-9fbb-56a63fb96846","discipline_id":"EAD344","period":8,"prerequisites":"","mandatory":true,"course_id":"engenharia-de-computacao"},{"id":"2bc26617-f67e-4fdc-96e1-e15099353b59","discipline_id":"CSI433","period":9,"prerequisites":"CSI548","mandatory":true,"course_id":"engenharia-de-computacao"},{"id":"83488624-6cc6-425e-8fc7-b3f751edc4ca","discipline_id":"CSI495","period":9,"prerequisites":"","mandatory":true,"course_id":"engenharia-de-computacao"},{"id":"1628620e-2a55-443e-9112-23102fb028d4","discipline_id":"CSI506","period":9,"prerequisites":"CSI476","mandatory":true,"course_id":"engenharia-de-computacao"},{"id":"902e74ae-c5aa-43c9-ac53-3ab44f7fee9c","discipline_id":"CSI510","period":9,"prerequisites":"CSI548","mandatory":true,"course_id":"engenharia-de-computacao"},{"id":"226019b8-755e-42ac-997c-98425cefadbc","discipline_id":"EAD351","period":9,"prerequisites":"","mandatory":true,"course_id":"engenharia-de-computacao"},{"id":"f85a5938-d383-4b71-a651-23f907ecd6ec c028e49c-393d-44cb-99eb-8ad1ceaaaf10","discipline_id":"CEA066","period":"10","prerequisites":"CEA038 CEA039 CEA062 CEA063","mandatory":true,"course_id":"engenharia-de-computacao"},{"id":"8d7df6de-7ea4-488b-be01-30c37892fed0","discipline_id":"CSI491","period":10,"prerequisites":"","mandatory":true,"course_id":"engenharia-de-computacao"},{"id":"516dd222-14b7-411c-958f-a0159aa6800a","discipline_id":"CSI496","period":10,"prerequisites":"CSI495","mandatory":true,"course_id":"engenharia-de-computacao"},{"id":"7cad2f70-0080-456b-b5b4-0b67cf7e004a","discipline_id":"CSI693","period":10,"prerequisites":"CSI433","mandatory":true,"course_id":"engenharia-de-computacao"},{"id":"ca2b144f-5b46-42a4-bd75-3f35b7dae3c6","discipline_id":"CEA026","period":"","prerequisites":"","mandatory":false,"course_id":"engenharia-de-computacao"},{"id":"23bf341b-053a-496c-8528-84b0e2d12816 233cc6c2-6241-42ac-a98e-e4fc22820f7a","discipline_id":"CEA057","period":"","prerequisites":"CEA052 CEA056","mandatory":false,"course_id":"engenharia-de-computacao"},{"id":"ef983bf3-4d39-4b28-9b45-68149ff05000","discipline_id":"CEA147","period":"","prerequisites":"CEA580","mandatory":false,"course_id":"engenharia-de-computacao"},{"id":"14816efe-3788-44bc-b57d-1a38595a2e95","discipline_id":"CEA453","period":"","prerequisites":"CEA562","mandatory":false,"course_id":"engenharia-de-computacao"},{"id":"65875da6-2191-4e52-8305-867a6e1e308f","discipline_id":"CEA563","period":"","prerequisites":"CEA552","mandatory":false,"course_id":"engenharia-de-computacao"},{"id":"27f4f352-d8b9-4986-becd-39502c83b8d8","discipline_id":"CEA570","period":"","prerequisites":"CEA562","mandatory":false,"course_id":"engenharia-de-computacao"},{"id":"82183e73-a451-4050-bebc-491ff1adcaaa","discipline_id":"CEA571","period":"","prerequisites":"CEA551 CEA561","mandatory":false,"course_id":"engenharia-de-computacao"},{"id":"f96a796b-724e-4a0e-8494-3728c62aaf80","discipline_id":"CEA572","period":"","prerequisites":"CEA561 CEA570","mandatory":false,"course_id":"engenharia-de-computacao"},{"id":"f1ea3947-21e4-464d-ae92-92dce15444b0","discipline_id":"CEA671","period":"","prerequisites":"CEA562","mandatory":false,"course_id":"engenharia-de-computacao"},{"id":"c6d772f8-5ba4-48c1-ada3-8cc6c85252e4","discipline_id":"CEA708","period":"","prerequisites":"CEA562","mandatory":false,"course_id":"engenharia-de-computacao"},{"id":"a50f3f93-8a08-451b-8286-456653f85027","discipline_id":"CEA709","period":"","prerequisites":"CEA502 CEA562","mandatory":false,"course_id":"engenharia-de-computacao"},{"id":"e9a60fd3-63ca-4569-b05f-7bcb75e1fde5 fcd620b2-25c1-4e9c-844c-d42f6ed800b3","discipline_id":"CEA710","period":"","prerequisites":"","mandatory":false,"course_id":"engenharia-de-computacao"},{"id":"a7f7e57e-06f3-4273-b51d-953946a720a0","discipline_id":"CEA711","period":"","prerequisites":"CEA341 CSI488","mandatory":false,"course_id":"engenharia-de-computacao"},{"id":"c249a8ae-ef8c-4979-8df6-b3b1fd02d6c9","discipline_id":"CEA712","period":"","prerequisites":"CEA562","mandatory":false,"course_id":"engenharia-de-computacao"},{"id":"cba09a06-9e0f-40a9-9cb8-ebfcae8ac2b7","discipline_id":"CSI001","period":"","prerequisites":"CSI466","mandatory":false,"course_id":"engenharia-de-computacao"},{"id":"65e7b0b6-6680-4aed-9cd3-8c531a83dc42","discipline_id":"CSI401","period":"","prerequisites":"","mandatory":false,"course_id":"engenharia-de-computacao"},{"id":"896fe309-4502-46fb-ae38-e2b512e15b1f","discipline_id":"CSI402","period":"","prerequisites":"","mandatory":false,"course_id":"engenharia-de-computacao"},{"id":"7a0a276b-47fa-4d0a-8130-492b21e38778","discipline_id":"CSI434","period":"","prerequisites":"CSI548","mandatory":false,"course_id":"engenharia-de-computacao"},{"id":"d05646f2-5c85-422a-812d-72b055c0ba83","discipline_id":"CSI436","period":"","prerequisites":"CSI440","mandatory":false,"course_id":"engenharia-de-computacao"},{"id":"cd63a8e1-1a78-4c58-92ad-0392a2a5242c","discipline_id":"CSI442","period":"","prerequisites":"CSI429 CSI440","mandatory":false,"course_id":"engenharia-de-computacao"},{"id":"30bacae6-12af-4670-9a71-7dd3782ef605","discipline_id":"CSI472","period":"","prerequisites":"CSI488","mandatory":false,"course_id":"engenharia-de-computacao"},{"id":"bb706c13-7ded-4da0-9a99-30d3a2bebf9d","discipline_id":"CSI477","period":"","prerequisites":"CSI440 CSI485 CSI548","mandatory":false,"course_id":"engenharia-de-computacao"},{"id":"6b2500a0-747e-4fb8-9840-669cb8e42d29","discipline_id":"CSI486","period":"","prerequisites":"CSI485","mandatory":false,"course_id":"engenharia-de-computacao"},{"id":"63d9118a-7a3a-4bda-a923-3291ef7531a9","discipline_id":"CSI501","period":"","prerequisites":"CEA341 CSI030","mandatory":false,"course_id":"engenharia-de-computacao"},{"id":"50cddb14-75d3-406f-9c21-9f5c51a62e9f","discipline_id":"CSI502","period":"","prerequisites":"CEA341 CSI030","mandatory":false,"course_id":"engenharia-de-computacao"},{"id":"e66655ff-95d3-454f-8491-debee6ece192","discipline_id":"CSI503","period":"","prerequisites":"CSI485","mandatory":false,"course_id":"engenharia-de-computacao"},{"id":"24d1c526-1046-4c71-8403-a7a8f2195f98","discipline_id":"CSI512","period":"","prerequisites":"CSI485","mandatory":false,"course_id":"engenharia-de-computacao"},{"id":"be670102-0a2a-4e59-a572-6f249812143f","discipline_id":"CSI513","period":"","prerequisites":"CSI440 CSI485","mandatory":false,"course_id":"engenharia-de-computacao"},{"id":"d3e46d57-c9ab-42ee-ba99-a0a5a3955d74","discipline_id":"CSI515","period":"","prerequisites":"CEA341 CEA562 CSI488","mandatory":false,"course_id":"engenharia-de-computacao"},{"id":"3e64f619-0d08-410f-883b-10b535bd45e6","discipline_id":"CSI516","period":"","prerequisites":"CSI486","mandatory":false,"course_id":"engenharia-de-computacao"},{"id":"a7fa4816-51f1-4aad-afa0-2f7b775281f5","discipline_id":"CSI518","period":"","prerequisites":"CSI486","mandatory":false,"course_id":"engenharia-de-computacao"},{"id":"8ec0498a-0856-4166-8f81-06fdee3e3bd9","discipline_id":"CSI520","period":"","prerequisites":"CSI032 CSI488","mandatory":false,"course_id":"engenharia-de-computacao"},{"id":"ff8184a6-0df2-4663-b083-5f4f00d826a7","discipline_id":"CSI549","period":"","prerequisites":"CSI450","mandatory":false,"course_id":"engenharia-de-computacao"},{"id":"884609fc-3f4f-4240-b046-37b85d4eb3a4","discipline_id":"CSI557","period":"","prerequisites":"CSI488","mandatory":false,"course_id":"engenharia-de-computacao"},{"id":"aaa49b47-bd41-4e8f-abda-b852e781e274","discipline_id":"CSI558","period":"","prerequisites":"CSI485","mandatory":false,"course_id":"engenharia-de-computacao"},{"id":"9c8e1d73-71d1-455c-bc05-f427a1e145c3","discipline_id":"CSI559","period":"","prerequisites":"CSI419","mandatory":false,"course_id":"engenharia-de-computacao"},{"id":"6e7378b1-633f-4d2a-82de-30bf8858145b 989d6ff0-8ba9-483e-9518-471a314115b1 ea15e2c6-b6e9-4e48-a079-7ea170853f7e","discipline_id":"CSI564","period":"","prerequisites":"CSI440","mandatory":false,"course_id":"engenharia-de-computacao"},{"id":"f75b9b6c-ab1d-465e-af73-a8a7c4c7ae3e dcf4584a-658c-460f-9cd6-9444f3408822","discipline_id":"CSI566","period":"","prerequisites":"CSI032 CSI488","mandatory":false,"course_id":"engenharia-de-computacao"},{"id":"c507e40b-9a04-4ecc-8b42-20aecbdcb289","discipline_id":"CSI567","period":"","prerequisites":"CSI485","mandatory":false,"course_id":"engenharia-de-computacao"},{"id":"40e316ae-0bb0-47dd-8aad-cadbc87c07b8","discipline_id":"CSI568","period":"","prerequisites":"CSI485","mandatory":false,"course_id":"engenharia-de-computacao"},{"id":"f468aa2c-b109-4ef8-b785-0a09c0c3375b","discipline_id":"CSI569","period":"","prerequisites":"CSI419","mandatory":false,"course_id":"engenharia-de-computacao"},{"id":"28135dd7-bfb3-47ad-8997-b57ac129be14","discipline_id":"CSI574","period":"","prerequisites":"CSI419","mandatory":false,"course_id":"engenharia-de-computacao"},{"id":"ddecc66e-51ff-436f-af0f-5ceb2497e187","discipline_id":"CSI575","period":"","prerequisites":"CSI477 CSI486","mandatory":false,"course_id":"engenharia-de-computacao"},{"id":"0f4c4af4-afe8-4eb2-89e8-9d5a8df9958d","discipline_id":"CSI576","period":"","prerequisites":"CSI485","mandatory":false,"course_id":"engenharia-de-computacao"},{"id":"8ef74ff0-3800-4c74-af11-30566802ab47","discipline_id":"CSI577","period":"","prerequisites":"CSI443 CSI488","mandatory":false,"course_id":"engenharia-de-computacao"},{"id":"128ca09f-19b5-4aff-8fd7-9c7d514bf459","discipline_id":"CSI578","period":"","prerequisites":"CSI419","mandatory":false,"course_id":"engenharia-de-computacao"},{"id":"461388bf-d67f-407b-881c-41a193a0c1bd","discipline_id":"CSI604","period":"","prerequisites":"CSI506","mandatory":false,"course_id":"engenharia-de-computacao"},{"id":"cd14610c-f704-442e-bb5d-3194a13ad882","discipline_id":"CSI730","period":"","prerequisites":"CSI032 CSI488","mandatory":false,"course_id":"engenharia-de-computacao"},{"id":"48aebbd2-64e6-4281-8999-1acecdeed892","discipline_id":"CSI731","period":"","prerequisites":"CSI440","mandatory":false,"course_id":"engenharia-de-computacao"},{"id":"cac9d4cb-4f6f-41b3-9902-8bffad16d659","discipline_id":"CSI732","period":"","prerequisites":"CSI419 CSI457","mandatory":false,"course_id":"engenharia-de-computacao"},{"id":"7236e90b-66ae-4429-9e74-2f69157faed8","discipline_id":"CSI733","period":"","prerequisites":"CSI457","mandatory":false,"course_id":"engenharia-de-computacao"},{"id":"ec24a63e-b8b1-41cd-b59f-8753fb610b0a","discipline_id":"CSI734","period":"","prerequisites":"CSI548","mandatory":false,"course_id":"engenharia-de-computacao"},{"id":"d54ccfe5-e7d9-4f30-8557-84c5f6102f76","discipline_id":"CSI735","period":"","prerequisites":"CSI440 CSI485","mandatory":false,"course_id":"engenharia-de-computacao"},{"id":"573cdebf-4b5e-4632-8fea-f306bb0e7df0","discipline_id":"ENP151","period":"","prerequisites":"","mandatory":false,"course_id":"engenharia-de-computacao"},{"id":"21121bb5-31f0-46d7-b84a-2970f698ccfc","discipline_id":"ENP152","period":"","prerequisites":"","mandatory":false,"course_id":"engenharia-de-computacao"},{"id":"261f0715-bd1a-4379-b5c3-5807374dbbfe","discipline_id":"ENP153","period":"","prerequisites":"CSI030 CSI488","mandatory":false,"course_id":"engenharia-de-computacao"},{"id":"bf97a190-9d6b-4594-8d25-e4c20e612d54","discipline_id":"ENP160","period":"","prerequisites":"ENP153","mandatory":false,"course_id":"engenharia-de-computacao"},{"id":"900578ab-7cdc-476d-8533-aba35d36a18c","discipline_id":"ENP493","period":"","prerequisites":"","mandatory":false,"course_id":"engenharia-de-computacao"},{"id":"8d547252-2553-4d11-b41e-3b27070d5a47 ecf0c586-8e96-4ecc-b226-218e06c77cd2","discipline_id":"LET966","period":"","prerequisites":"","mandatory":false,"course_id":"engenharia-de-computacao"},{"id":"8f8c50b4-185c-4605-8fa0-7e559a11819e","discipline_id":"CEA453","period":"","prerequisites":"CEA562","mandatory":false,"course_id":"engenharia-de-computacao"},{"id":"bfe0dbbc-3d36-46ef-8ce3-5c01fa69d863","discipline_id":"CEA708","period":"","prerequisites":"CEA562","mandatory":false,"course_id":"engenharia-de-computacao"},{"id":"4720a4ae-f15b-4b4a-bb0e-ac2970e28b24","discipline_id":"CEA709","period":"","prerequisites":"CEA502 CEA562","mandatory":false,"course_id":"engenharia-de-computacao"},{"id":"54dec1ec-02ac-4ed0-9d7b-8b86f69a39ad 905af58a-38d4-48ab-a2f2-3c4c793afefd","discipline_id":"CEA710","period":"","prerequisites":"","mandatory":false,"course_id":"engenharia-de-computacao"},{"id":"65e4c281-d650-4d1d-b969-05d8bdf8eb92","discipline_id":"CEA711","period":"","prerequisites":"CEA341 CSI488","mandatory":false,"course_id":"engenharia-de-computacao"},{"id":"10baadb9-48f3-42a7-ac21-42841ac1a491","discipline_id":"CEA712","period":"","prerequisites":"CEA562","mandatory":false,"course_id":"engenharia-de-computacao"},{"id":"8602a2e5-369f-4998-aa20-6048f91baf55 cdcedd76-5c73-403b-90fc-8bf0d481e453","discipline_id":"CSI515","period":"","prerequisites":"CEA341 CEA562 CSI488","mandatory":false,"course_id":"engenharia-de-computacao"},{"id":"ad61d630-785b-4368-a68d-5a9e81127c71","discipline_id":"CSI436","period":"","prerequisites":"CSI440","mandatory":false,"course_id":"engenharia-de-computacao"},{"id":"6b8e5da3-0afc-4f3a-8ed8-fe36d72ed9f1","discipline_id":"CSI442","period":"","prerequisites":"CSI429 CSI440","mandatory":false,"course_id":"engenharia-de-computacao"},{"id":"e6464356-e3e8-44f0-a17f-95f7dafe6534","discipline_id":"CSI472","period":"","prerequisites":"CSI488","mandatory":false,"course_id":"engenharia-de-computacao"},{"id":"f1c94d5c-5ad8-4d77-ae76-a7e86817b764","discipline_id":"CSI477","period":"","prerequisites":"CSI440 CSI485 CSI548","mandatory":false,"course_id":"engenharia-de-computacao"},{"id":"7d4fe3b1-9d54-46eb-a1f8-d9c7e506d51a","discipline_id":"CSI486","period":"","prerequisites":"CSI485","mandatory":false,"course_id":"engenharia-de-computacao"},{"id":"4e45b656-ae1b-4a9b-ad94-5a2c4eb813e0","discipline_id":"CSI512","period":"","prerequisites":"CSI485","mandatory":false,"course_id":"engenharia-de-computacao"},{"id":"9a3c46ba-0229-41d0-995f-d5b6dd28b821","discipline_id":"CSI513","period":"","prerequisites":"CSI440 CSI485","mandatory":false,"course_id":"engenharia-de-computacao"},{"id":"65f5cac6-ae60-4f4c-98c0-e9d112ae01c3","discipline_id":"CSI516","period":"","prerequisites":"CSI486","mandatory":false,"course_id":"engenharia-de-computacao"},{"id":"a8e2ab4d-2b2e-4053-9ee6-85652078d8e5","discipline_id":"CSI518","period":"","prerequisites":"CSI486","mandatory":false,"course_id":"engenharia-de-computacao"},{"id":"5b89c0a3-a9cb-4756-8aca-a1376d01489c","discipline_id":"CSI549","period":"","prerequisites":"CSI450","mandatory":false,"course_id":"engenharia-de-computacao"},{"id":"b9fab5f1-f5ce-4b40-87f1-f816cc7de075","discipline_id":"CSI557","period":"","prerequisites":"CSI488","mandatory":false,"course_id":"engenharia-de-computacao"},{"id":"26576087-f25e-45f1-80ee-4690f6a0a890","discipline_id":"CSI558","period":"","prerequisites":"CSI485","mandatory":false,"course_id":"engenharia-de-computacao"},{"id":"5f25ac23-d24f-448f-b920-0730aa448bda 3397abf3-788e-4b6f-8a35-270a3cb96c16 4fe8da87-9926-41f9-9647-c9153bf111a3","discipline_id":"CSI564","period":"","prerequisites":"CSI440","mandatory":false,"course_id":"engenharia-de-computacao"},{"id":"0cbdb2ca-a197-4412-ad18-fe0fb6f3e7ec","discipline_id":"CSI567","period":"","prerequisites":"CSI485","mandatory":false,"course_id":"engenharia-de-computacao"},{"id":"8d9bc6f1-b7bf-4147-a4e5-37a865b153fd","discipline_id":"CSI568","period":"","prerequisites":"CSI485","mandatory":false,"course_id":"engenharia-de-computacao"},{"id":"2dbb3a0e-9a23-4be2-a088-4b8d375fdc17","discipline_id":"CSI575","period":"","prerequisites":"CSI477 CSI486","mandatory":false,"course_id":"engenharia-de-computacao"},{"id":"126d9648-8125-4a1d-ad2d-0cad5f8e6a06","discipline_id":"CSI576","period":"","prerequisites":"CSI485","mandatory":false,"course_id":"engenharia-de-computacao"}]